MANIFEST.in
README.md
setup.cfg
setup.py
flipsyrup/__init__.py
flipsyrup/flipsyrup.py
flipsyrup.egg-info/PKG-INFO
flipsyrup.egg-info/SOURCES.txt
flipsyrup.egg-info/dependency_links.txt
flipsyrup.egg-info/entry_points.txt
flipsyrup.egg-info/top_level.txt
flipsyrup/abstract_channel/__init__.py
flipsyrup/abstract_channel/abstract_channel.py
flipsyrup/abstract_channel/template/__init__.py
flipsyrup/abstract_channel/template/channel.txt
flipsyrup/abstract_memory/__init__.py
flipsyrup/abstract_memory/abstract_memory.py
flipsyrup/abstract_memory/controller_generator.py
flipsyrup/abstract_memory/counter_generator.py
flipsyrup/abstract_memory/memory_generator.py
flipsyrup/abstract_memory/system_generator.py
flipsyrup/abstract_memory/template/__init__.py
flipsyrup/abstract_memory/template/addressmapper.v
flipsyrup/abstract_memory/template/banked_cache.v
flipsyrup/abstract_memory/template/cache.v
flipsyrup/abstract_memory/template/counter.v
flipsyrup/abstract_memory/template/domaincontroller.v
flipsyrup/abstract_memory/template/jinja_addressmapper.py
flipsyrup/abstract_memory/template/jinja_banked_cache.py
flipsyrup/abstract_memory/template/jinja_cache.py
flipsyrup/abstract_memory/template/jinja_counter.py
flipsyrup/abstract_memory/template/jinja_domaincontroller.py
flipsyrup/abstract_memory/template/jinja_marshaller.py
flipsyrup/abstract_memory/template/jinja_offchipmemory.py
flipsyrup/abstract_memory/template/jinja_scratchpad.py
flipsyrup/abstract_memory/template/jinja_scratchpad_mask.py
flipsyrup/abstract_memory/template/jinja_scratchpad_mux.py
flipsyrup/abstract_memory/template/jinja_system.py
flipsyrup/abstract_memory/template/marshaller.v
flipsyrup/abstract_memory/template/merged_cache.v
flipsyrup/abstract_memory/template/offchipmemory.v
flipsyrup/abstract_memory/template/scratchpad.v
flipsyrup/abstract_memory/template/scratchpad_mask.v
flipsyrup/abstract_memory/template/scratchpad_mux.v
flipsyrup/abstract_memory/template/system.v
flipsyrup/configuration_reader/__init__.py
flipsyrup/configuration_reader/configuration_reader.py
flipsyrup/configuration_reader/domain_generator.py
flipsyrup/configuration_reader/resource_definition.py
