Metadata-Version: 1.0
Name: flipsyrup
Version: 0.9.0
Summary: Cycle-Accurate Hardware Simulation Framework on Abstract FPGA Platforms
Home-page: http://shtaxxx.github.io/flipSyrup/
Author: Shinya Takamaeda-Yamazaki
Author-email: shinya.takamaeda_at_gmail_com
License: Apache License 2.0
Platform: UNKNOWN
